README.md
pyproject.toml
setup.py
elasticsearch/__init__.py
elasticsearch/__init__.pyi
elasticsearch/_version.py
elasticsearch/compat.py
elasticsearch/compat.pyi
elasticsearch/connection_pool.py
elasticsearch/connection_pool.pyi
elasticsearch/exceptions.py
elasticsearch/exceptions.pyi
elasticsearch/py.typed
elasticsearch/serializer.py
elasticsearch/serializer.pyi
elasticsearch/transport.py
elasticsearch/transport.pyi
elasticsearch/utils.py
elasticsearch/utils.pyi
elasticsearch/_async/__init__.py
elasticsearch/_async/_extra_imports.py
elasticsearch/_async/compat.py
elasticsearch/_async/compat.pyi
elasticsearch/_async/helpers.py
elasticsearch/_async/helpers.pyi
elasticsearch/_async/http_aiohttp.py
elasticsearch/_async/http_aiohttp.pyi
elasticsearch/_async/transport.py
elasticsearch/_async/transport.pyi
elasticsearch/_async/client/__init__.py
elasticsearch/_async/client/__init__.pyi
elasticsearch/_async/client/async_search.py
elasticsearch/_async/client/async_search.pyi
elasticsearch/_async/client/autoscaling.py
elasticsearch/_async/client/autoscaling.pyi
elasticsearch/_async/client/cat.py
elasticsearch/_async/client/cat.pyi
elasticsearch/_async/client/ccr.py
elasticsearch/_async/client/ccr.pyi
elasticsearch/_async/client/cluster.py
elasticsearch/_async/client/cluster.pyi
elasticsearch/_async/client/dangling_indices.py
elasticsearch/_async/client/dangling_indices.pyi
elasticsearch/_async/client/data_frame.py
elasticsearch/_async/client/data_frame.pyi
elasticsearch/_async/client/deprecation.py
elasticsearch/_async/client/deprecation.pyi
elasticsearch/_async/client/enrich.py
elasticsearch/_async/client/enrich.pyi
elasticsearch/_async/client/eql.py
elasticsearch/_async/client/eql.pyi
elasticsearch/_async/client/features.py
elasticsearch/_async/client/features.pyi
elasticsearch/_async/client/fleet.py
elasticsearch/_async/client/fleet.pyi
elasticsearch/_async/client/graph.py
elasticsearch/_async/client/graph.pyi
elasticsearch/_async/client/ilm.py
mobio_elasticsearch7_test.egg-info/PKG-INFO
mobio_elasticsearch7_test.egg-info/SOURCES.txt
mobio_elasticsearch7_test.egg-info/dependency_links.txt
mobio_elasticsearch7_test.egg-info/requires.txt
mobio_elasticsearch7_test.egg-info/top_level.txt